<alarm type="opus1"><defect><did>1.2.79.0</did><dloc><file>/home/kskyj/sparrow4/util/testcode/c/NEGATIVE_FILE_DESCRIPTOR.c</file><filehash>820a4652742e9aaca68f7cff85a61f36bed5313b.NEGATIVE_FILE_DESCRIPTOR.c</filehash><line_src>7</line_src><line_sink>11</line_sink><func>negative_file_des</func></dloc><type>RESOURCE_INJECTION</type><rank><path_len>0</path_len><path_num>1</path_num></rank><events><bid>1.0</bid><bid>2.0</bid></events><start><cid>0</cid><bid>1.0</bid></start><determinant>41a65555ecdd900b804beb3bc84f7a598e93275a</determinant></defect><ctx><cid>0</cid><cloc><file>/home/kskyj/sparrow4/util/testcode/c/NEGATIVE_FILE_DESCRIPTOR.c</file><filehash>820a4652742e9aaca68f7cff85a61f36bed5313b.NEGATIVE_FILE_DESCRIPTOR.c</filehash><line_start>6</line_start><line_end>16</line_end><func>negative_file_des</func></cloc><bid>1.0</bid><bid>2.0</bid></ctx><box><bid>1.0</bid><bloc><file>/home/kskyj/sparrow4/util/testcode/c/NEGATIVE_FILE_DESCRIPTOR.c</file><filehash>820a4652742e9aaca68f7cff85a61f36bed5313b.NEGATIVE_FILE_DESCRIPTOR.c</filehash><line>7</line><func>negative_file_des</func><exp>rPort = getenv(\"rPort\")</exp></bloc><event><msg>The port number of socket function getenv is made from external environments</msg><desc id="opus1.RESOURCE_INJECTION.src1"><arg>function getenv</arg></desc></event></box><box><bid>2.0</bid><bloc><file>/home/kskyj/sparrow4/util/testcode/c/NEGATIVE_FILE_DESCRIPTOR.c</file><filehash>820a4652742e9aaca68f7cff85a61f36bed5313b.NEGATIVE_FILE_DESCRIPTOR.c</filehash><line>11</line><func>negative_file_des</func><exp>buf</exp></bloc><event><msg>The network socket function getenv using number from external environemnts is created</msg><desc id="opus1.RESOURCE_INJECTION.sink1"><arg>function getenv</arg></desc></event></box></alarm>